Zero-DCE/Myloss.py
Zero-DCE/__init__.py
Zero-DCE/dataloader.py
Zero-DCE/lowlight_test.py
Zero-DCE/lowlight_train.py
Zero-DCE/model.py
zero_dce/Myloss.py
zero_dce/__init__.py
zero_dce/dataloader.py
zero_dce/lowlight_test.py
zero_dce/lowlight_train.py
zero_dce/model.py
zero_dce-1.0.0.dist-info/METADATA
zero_dce-1.0.0.dist-info/WHEEL
zero_dce-1.0.0.dist-info/top_level.txt
zero_dce-1.0.0.dist-info/RECORD
