Metadata-Version: 2.1
Name: zero-dce
Version: 1.0.0
Summary: Zero-Reference Deep Curve Estimation for Low-Light Image Enhancement
Home-page: https://github.com/leonelhs/Zero-DCE
Author: leonel hernandez
Author-email: leonelhs@gmail.com
License: Apache
Classifier: Development Status :: 5 - Production/Stable
Classifier: Intended Audience :: Developers
Classifier: Intended Audience :: Science/Research
Classifier: Natural Language :: English
Classifier: Operating System :: OS Independent
Classifier: Programming Language :: Python
Classifier: Programming Language :: Python :: 3.5
Classifier: Programming Language :: Python :: 3.6
Classifier: Programming Language :: Python :: 3.7
Classifier: Programming Language :: Python :: 3.8
Classifier: Programming Language :: Python :: 3.9
Classifier: Programming Language :: Python :: 3 :: Only
Requires-Dist: torch (>=2.0.0)
